ecom_data_helpers/__init__.py
ecom_data_helpers/common_aws.py
ecom_data_helpers/common_utils.py
ecom_data_helpers/document_extraction.py
ecom_data_helpers/energy_account_extraction.py
ecom_data_helpers/exceptions.py
ecom_data_helpers/utils.py
tests/__init__.py
tests/test_ecom_data_helpers_document_extraction.py
tests/test_ecom_data_helpers_energy_account_extraction.py
ecom_data_helpers_lib-0.0.49.dist-info/LICENSE
ecom_data_helpers_lib-0.0.49.dist-info/METADATA
ecom_data_helpers_lib-0.0.49.dist-info/WHEEL
ecom_data_helpers_lib-0.0.49.dist-info/top_level.txt
ecom_data_helpers_lib-0.0.49.dist-info/RECORD
