Metadata-Version: 2.1
Name: ecom_data_helpers_lib
Version: 0.0.49
Summary: A library of reusable utilities for AWS Lambda functions in ECOM Data Projects
Home-page: https://github.com/ecom-one-stop-solution/ecom-data-helpers-lib
Author: Augusto Lorencatto
Author-email: augusto.lorencatto@ecomenergia.com.br
Classifier: Programming Language :: Python :: 3
Classifier: License :: OSI Approved :: MIT License
Classifier: Operating System :: OS Independent
Requires-Python: >=3.12
License-File: LICENSE
Requires-Dist: boto3
Requires-Dist: python-docx==1.1.2
Requires-Dist: PyPDF2==3.0.1
Requires-Dist: pdf2image==1.17.0
Requires-Dist: pytest
Requires-Dist: httpx
Requires-Dist: pandas
